conver/__init__.py
conver/main.py
TDMS_Conver-0.0.1.dist-info/METADATA
TDMS_Conver-0.0.1.dist-info/WHEEL
TDMS_Conver-0.0.1.dist-info/entry_points.txt
TDMS_Conver-0.0.1.dist-info/top_level.txt
TDMS_Conver-0.0.1.dist-info/RECORD
