Metadata-Version: 2.1
Name: TDMS-Conver
Version: 0.0.1
Summary: A small example package
Home-page: https://github.com/Littleor/TDMS-Conver.git
Author: Littleor
Author-email: me@littleor.cn
License: MIT
Platform: UNKNOWN
Classifier: Programming Language :: Python
Classifier: Programming Language :: Python :: 3
Classifier: Programming Language :: Python :: 3.6
Classifier: Programming Language :: Python :: Implementation :: CPython
Classifier: Programming Language :: Python :: Implementation :: PyPy
Classifier: License :: OSI Approved :: MIT License
Requires-Dist: pandas (>=1.1.5)
Requires-Dist: openpyxl (>=3.0.7)
Requires-Dist: npTDMS (>=1.3.0)
